{
    "homepage": "https://www.cockroachlabs.com/",
    "description": "The SQL database for global cloud services",
    "license": {
        "identifier": "Apache-2.0,BSD-3-Clause,MIT,Freeware",
        "url": "https://github.com/cockroachdb/cockroach/blob/master/LICENSE"
    },
    "version": "2.1.4",
    "url": "https://binaries.cockroachdb.com/cockroach-v2.1.4.windows-6.2-amd64.zip",
    "hash": "9e040cb1644127dd1ccba7a01d58930c37199a788d633e845fdeffe17d0d8d31",
    "extract_dir": "cockroach-v2.1.4.windows-6.2-amd64",
    "bin": "cockroach.exe",
    "checkver": {
        "url": "https://www.cockroachlabs.com/docs/stable/install-cockroachdb.html",
        "re": "\"version-name\">v([\\d.]+)<"
    },
    "autoupdate": {
        "url": "https://binaries.cockroachdb.com/cockroach-v$version.windows-6.2-amd64.zip",
        "extract_dir": "cockroach-v$version.windows-6.2-amd64"
    }
}
