{
    "homepage": "https://curl.haxx.se/",
    "description": "Command line tool and library for transferring data with URLs",
    "version": "7.61.0",
    "license": "MIT",
    "architecture": {
        "64bit": {
            "url": "https://dl.bintray.com/vszakats/generic/curl-7.61.0-win64-mingw.tar.xz",
            "hash": "c03495199d101f5942f783bdf4af705f6d80093e5d287571fc314cd7d4ca35c2",
            "extract_dir": "curl-7.61.0-win64-mingw"
        },
        "32bit": {
            "url": "https://dl.bintray.com/vszakats/generic/curl-7.61.0-win32-mingw.tar.xz",
            "hash": "6168e55641a5b117610724a7fff8006cd89e205e37553719e9f4f2bd7f56ba5c",
            "extract_dir": "curl-7.61.0-win32-mingw"
        }
    },
    "bin": "bin\\curl.exe",
    "checkver": {
        "url": "https://api.bintray.com/packages/vszakats/generic/curl",
        "jp": "$.latest_version"
    },
    "suggest": {
        "cacert": [
            "cacert"
        ]
    },
    "autoupdate": {
        "architecture": {
            "64bit": {
                "url": "https://dl.bintray.com/vszakats/generic/curl-$version-win64-mingw.tar.xz",
                "extract_dir": "curl-$version-win64-mingw"
            },
            "32bit": {
                "url": "https://dl.bintray.com/vszakats/generic/curl-$version-win32-mingw.tar.xz",
                "extract_dir": "curl-$version-win32-mingw"
            }
        },
        "hash": {
            "url": "$url.sha256"
        }
    }
}
