{
    "homepage": "https://github.com/sass/dart-sass",
    "version": "1.5.1",
    "license": "MIT",
    "architecture": {
        "64bit": {
            "url": "https://github.com/sass/dart-sass/releases/download/1.5.1/dart-sass-1.5.1-windows-x64.zip",
            "hash": "23b98d530bca2d4843d5ab22b4440b7cccd6ecc78fc9403c350a5572f87e8a7a"
        },
        "32bit": {
            "url": "https://github.com/sass/dart-sass/releases/download/1.5.1/dart-sass-1.5.1-windows-ia32.zip",
            "hash": "a4f73418b82d20f694ae8dd07ed904b45e4a9b10a0e8cbca8465389b9147f2e0"
        }
    },
    "extract_dir": "dart-sass",
    "bin": [
        "dart-sass.bat"
    ],
    "checkver": {
        "url": "https://github.com/sass/dart-sass/releases/latest",
        "re": "/releases/tag/(?:v)?([\\d\\w.-]+)"
    },
    "autoupdate": {
        "architecture": {
            "64bit": {
                "url": "https://github.com/sass/dart-sass/releases/download/$version/dart-sass-$version-windows-x64.zip"
            },
            "32bit": {
                "url": "https://github.com/sass/dart-sass/releases/download/$version/dart-sass-$version-windows-ia32.zip"
            }
        }
    }
}
