{
    "homepage": "https://www.openfaas.com/",
    "license": "MIT",
    "version": "0.8.8",
    "architecture": {
        "64bit": {
            "url": "https://github.com/openfaas/faas-cli/releases/download/0.8.8/faas-cli.exe",
            "hash": "41779107b3aa0be18409e673d51d9d5812b08ff977d0670d534678fbc55c713d"
        }
    },
    "bin": [
        "faas-cli.exe",
        [
            "faas-cli.exe",
            "faas"
        ]
    ],
    "post_install": "faas-cli version",
    "notes": "OpenFaas @ https://www.openfaas.com/",
    "checkver": {
        "github": "https://github.com/openfaas/faas-cli"
    },
    "autoupdate": {
        "architecture": {
            "64bit": {
                "url": "https://github.com/openfaas/faas-cli/releases/download/$version/faas-cli.exe"
            }
        }
    }
}
