{
    "version": "0.38",
    "license": "https://github.com/spf13/hugo/blob/master/LICENSE.md",
    "architecture": {
        "64bit": {
            "url": "https://github.com/spf13/hugo/releases/download/v0.38/hugo_0.38_windows-64bit.zip",
            "hash": "898bb17d023178040e0d8b748a762d092f3678528c4a44e07a9b56cfe7debfd8"
        },
        "32bit": {
            "url": "https://github.com/spf13/hugo/releases/download/v0.38/hugo_0.38_windows-32bit.zip",
            "hash": "c36b2c5ee1d7a5fd556f9c4dc22710dfe21c6048767898a74de09bad41a14505"
        }
    },
    "bin": "hugo.exe",
    "homepage": "https://gohugo.io",
    "checkver": {
        "github": "https://github.com/spf13/hugo"
    },
    "autoupdate": {
        "architecture": {
            "64bit": {
                "url": "https://github.com/spf13/hugo/releases/download/v$version/hugo_$version_windows-64bit.zip"
            },
            "32bit": {
                "url": "https://github.com/spf13/hugo/releases/download/v$version/hugo_$version_windows-32bit.zip"
            }
        },
        "hash": {
            "url": "https://github.com/spf13/hugo/releases/download/v$version/hugo_$version_checksums.txt"
        }
    }
}
