{
    "homepage": "https://github.com/jenkins-x/jx",
    "description": "A command line tool for installing and using Jenkins X",
    "license": "Apache-2.0",
    "version": "1.3.927",
    "architecture": {
        "64bit": {
            "url": "https://github.com/jenkins-x/jx/releases/download/v1.3.927/jx-windows-amd64.zip",
            "hash": "0615d0f67cf9a7a668637a5aa7af469479f6aa9b086e1971693f15c00e83cadc"
        }
    },
    "bin": [
        [
            "jx-windows-amd64.exe",
            "jx"
        ]
    ],
    "checkver": "github",
    "autoupdate": {
        "architecture": {
            "64bit": {
                "url": "https://github.com/jenkins-x/jx/releases/download/v$version/jx-windows-amd64.zip"
            }
        },
        "hash": {
            "url": "$url.sha256"
        }
    },
    "pre_install": "Stop-Process -Name jx -Verbose -ErrorAction Ignore"
}
