{
    "homepage": "https://minio.io/",
    "license": "Apache-2.0",
    "version": "2018-10-31T22-15-44Z",
    "bin": "mc.exe",
    "architecture": {
        "64bit": {
            "url": "https://dl.minio.io/client/mc/release/windows-amd64/mc.RELEASE.2018-10-31T22-15-44Z#/mc.exe",
            "hash": "fb0af01095b348b4fb824722071237c6ce7f982801100a873fec05ba03dc382c"
        }
    },
    "suggest": {
        "minio": "minio"
    },
    "checkver": {
        "github": "https://github.com/minio/mc",
        "re": "releases/tag/RELEASE.([\\d-]+T[\\d-]+Z)"
    },
    "autoupdate": {
        "architecture": {
            "64bit": {
                "url": "https://dl.minio.io/client/mc/release/windows-amd64/mc.RELEASE.$version#/mc.exe",
                "hash": {
                    "url": "$baseurl/mc.exe.sha256sum"
                }
            }
        }
    }
}
