{
    "version": "5.12.0.226",
    "homepage": "http://www.mono-project.com/",
    "license": "MIT",
    "url": "https://download.mono-project.com/archive/5.12.0/windows-installer/mono-5.12.0.226-gtksharp-2.12.45-win32-0.msi",
    "hash": "93fa94148a1198aa2365dee993c682918acd321a1844c9aea4d198b2483a144a",
    "extract_dir": "Mono",
    "env_add_path": "bin",
    "checkver": {
        "url": "http://www.mono-project.com/download/stable/",
        "re": "(?<short>[\\d.]+)/windows-installer/(?<file>mono-(?<version>[\\d.]+).*win32.*).msi"
    },
    "autoupdate": {
        "url": "https://download.mono-project.com/archive/$matchShort/windows-installer/$matchFile.msi"
    }
}
