{
    "autoupdate": {
        "url": "http://blog.alivate.com.au/wp-content/uploads/$matchDate/poppler-$version_x86.7z"
    },
    "bin": [
        "bin/pdfdetach.exe",
        "bin/pdffonts.exe",
        "bin/pdfimages.exe",
        "bin/pdfinfo.exe",
        "bin/pdfseparate.exe",
        "bin/pdftocairo.exe",
        "bin/pdftohtml.exe",
        "bin/pdftoppm.exe",
        "bin/pdftops.exe",
        "bin/pdftotext.exe",
        "bin/pdfunite.exe"
    ],
    "checkver": "Latest.*uploads/(?<date>\\d{4}/\\d{2})/poppler-(?<version>[\\d.]+)_x86.7z",
    "description": "PDF rendering library",
    "extract_dir": "poppler-0.51",
    "hash": "75d3b50ee810222376778d0cde88f44a61d723935a938efbb6cf9d8b6c067ac9",
    "homepage": "http://blog.alivate.com.au/poppler-windows/",
    "license": "GPL-3.0",
    "url": "http://blog.alivate.com.au/wp-content/uploads/2018/08/poppler-0.54_x86.7z",
    "version": "0.54"
}
