{
    "homepage": "https://qemu.weilnetz.de/",
    "license": "GPL-2.0",
    "version": "2.12.0-rc3",
    "architecture": {
        "64bit": {
            "url": "https://qemu.weilnetz.de/w64/qemu-w64-setup-20180412.exe#/dl.7z",
            "hash": "sha512:4da8b39919fb7485a1921102d26c1b94f3b868e7f40e50831c21b265b992a78bcf01fa3a7167b1c6b6025d8682909628c254aa4dc043c52143c71c6ac71083a3"
        },
        "32bit": {
            "url": "https://qemu.weilnetz.de/w32/qemu-w32-setup-20180412.exe#/dl.7z",
            "hash": "sha512:87e51e491579d2c7e61e18ff7fc2618ec21eb0b3e97eeb331db9a215cbafd49ff148d615a5d00f3b129eca480465866354ee8e53555eb11fc7b4206aee74328b"
        }
    },
    "bin": [
        "qemu-img.exe",
        "qemu-io.exe",
        "qemu-system-aarch64.exe",
        "qemu-system-aarch64w.exe",
        "qemu-system-alpha.exe",
        "qemu-system-alphaw.exe",
        "qemu-system-arm.exe",
        "qemu-system-armw.exe",
        "qemu-system-cris.exe",
        "qemu-system-crisw.exe",
        "qemu-system-i386.exe",
        "qemu-system-i386w.exe",
        "qemu-system-lm32.exe",
        "qemu-system-lm32w.exe",
        "qemu-system-m68k.exe",
        "qemu-system-m68kw.exe",
        "qemu-system-microblaze.exe",
        "qemu-system-microblazeel.exe",
        "qemu-system-microblazeelw.exe",
        "qemu-system-microblazew.exe",
        "qemu-system-mips.exe",
        "qemu-system-mips64.exe",
        "qemu-system-mips64el.exe",
        "qemu-system-mips64elw.exe",
        "qemu-system-mips64w.exe",
        "qemu-system-mipsel.exe",
        "qemu-system-mipselw.exe",
        "qemu-system-mipsw.exe",
        "qemu-system-moxie.exe",
        "qemu-system-moxiew.exe",
        "qemu-system-nios2.exe",
        "qemu-system-nios2w.exe",
        "qemu-system-or1k.exe",
        "qemu-system-or1kw.exe",
        "qemu-system-ppc.exe",
        "qemu-system-ppc64.exe",
        "qemu-system-ppc64w.exe",
        "qemu-system-ppcemb.exe",
        "qemu-system-ppcembw.exe",
        "qemu-system-ppcw.exe",
        "qemu-system-s390x.exe",
        "qemu-system-s390xw.exe",
        "qemu-system-sh4.exe",
        "qemu-system-sh4eb.exe",
        "qemu-system-sh4ebw.exe",
        "qemu-system-sh4w.exe",
        "qemu-system-sparc.exe",
        "qemu-system-sparc64.exe",
        "qemu-system-sparc64w.exe",
        "qemu-system-sparcw.exe",
        "qemu-system-tricore.exe",
        "qemu-system-tricorew.exe",
        "qemu-system-unicore32.exe",
        "qemu-system-unicore32w.exe",
        "qemu-system-x86_64.exe",
        "qemu-system-x86_64w.exe",
        "qemu-system-xtensa.exe",
        "qemu-system-xtensaeb.exe",
        "qemu-system-xtensaebw.exe",
        "qemu-system-xtensaw.exe"
    ],
    "checkver": {
        "re": "<strong>(?<year>\\d{4})-(?<month>\\d{2})-(?<day>\\d{2})</strong>: New QEMU installers \\((?<version>[\\d.a-z\\-]+)\\)"
    },
    "autoupdate": {
        "architecture": {
            "64bit": {
                "url": "https://qemu.weilnetz.de/w64/qemu-w64-setup-$matchYear$matchMonth$matchDay.exe#/dl.7z",
                "hash": {
                    "url": "https://qemu.weilnetz.de/w64/qemu-w64-setup-$matchYear$matchMonth$matchDay.sha512"
                }
            },
            "32bit": {
                "url": "https://qemu.weilnetz.de/w32/qemu-w32-setup-$matchYear$matchMonth$matchDay.exe#/dl.7z",
                "hash": {
                    "url": "https://qemu.weilnetz.de/w32/qemu-w32-setup-$matchYear$matchMonth$matchDay.sha512"
                }
            }
        }
    }
}
