{
    "homepage": "https://www.scala-lang.org/",
    "version": "2.12.5",
    "license": "BSD-3-Clause",
    "url": "https://downloads.typesafe.com/scala/2.12.5/scala-2.12.5.zip",
    "hash": "98d9e46f8ebe3696739a2016e0d763877c0242b265bb7cce9ee3ac828fe2bb14",
    "extract_dir": "scala-2.12.5",
    "bin": [
        "bin\\fsc.bat",
        "bin\\scala.bat",
        "bin\\scalac.bat",
        "bin\\scaladoc.bat",
        "bin\\scalap.bat"
    ],
    "env_set": {
        "SCALA_HOME": "$dir"
    },
    "suggest": {
        "JDK": [
            "java/oraclejdk",
            "java/openjdk"
        ]
    },
    "checkver": {
        "url": "https://www.scala-lang.org/download/",
        "re": "scala-([\\d.]+).zip"
    },
    "autoupdate": {
        "url": "https://downloads.typesafe.com/scala/$version/scala-$version.zip",
        "extract_dir": "scala-$version"
    }
}
